reader/__init__.py
reader/__main__.py
reader/config.cfg
reader/feed.py
reader/viewer.py
lightmgb-1.0.0.dist-info/LICENSE
lightmgb-1.0.0.dist-info/METADATA
lightmgb-1.0.0.dist-info/WHEEL
lightmgb-1.0.0.dist-info/entry_points.txt
lightmgb-1.0.0.dist-info/top_level.txt
lightmgb-1.0.0.dist-info/RECORD
