Metadata-Version: 2.1
Name: lightmgb
Version: 1.0.0
Summary: Read the latest Real Python tutorials
Home-page: https://github.com/SOOS-Pchen/reader
Author: PJC Bro
Author-email: pchen@soos.io
License: MIT
Platform: UNKNOWN
Classifier: License :: OSI Approved :: MIT License
Classifier: Programming Language :: Python
Classifier: Programming Language :: Python :: 3
Requires-Dist: feedparser
Requires-Dist: html2text
